klingon_deps/__init__.py
klingon_deps/cli.py
klingon_deps/config_manager.py
klingon_deps/dependency_manager.py
klingon_deps/language_detector.py
klingon_deps-0.1.0.dist-info/LICENSE
klingon_deps-0.1.0.dist-info/METADATA
klingon_deps-0.1.0.dist-info/WHEEL
klingon_deps-0.1.0.dist-info/entry_points.txt
klingon_deps-0.1.0.dist-info/top_level.txt
klingon_deps-0.1.0.dist-info/RECORD
