Metadata-Version: 2.1
Name: klingon_deps
Version: 0.1.0
License-File: LICENSE
Requires-Dist: pyyaml
